funcargpreprocessor/__init__.py
funcargpreprocessor/customtypearg.py
funcargpreprocessor/errorcode.py
funcargpreprocessor/exceptions.py
funcargpreprocessor/funcargpreprocesser.py
funcargpreprocessor-0.10.3.dist-info/LICENSE
funcargpreprocessor-0.10.3.dist-info/METADATA
funcargpreprocessor-0.10.3.dist-info/WHEEL
funcargpreprocessor-0.10.3.dist-info/top_level.txt
funcargpreprocessor-0.10.3.dist-info/RECORD
