Metadata-Version: 2.1
Name: funcargpreprocessor
Version: 0.10.3
Summary: Parser for function arguments
Home-page: https://github.com/sabariramc/funcargpreprocessor
Author: Sabariram
Author-email: c.sabariram@gmail.com
License: MIT Licence
Platform: UNKNOWN
Classifier: Intended Audience :: Developers
Classifier: Operating System :: OS Independent
Classifier: Programming Language :: Python :: 3.6
Classifier: Programming Language :: Python :: 3.7
Classifier: Programming Language :: Python :: 3.8
Classifier: Topic :: Software Development :: Libraries :: Python Modules
Classifier: License :: OSI Approved :: MIT License
Requires-Python: >=3.6
